LICENSE
MANIFEST.in
README.md
pyproject.toml
setup.py
boxhed_shap/__init__.py
boxhed_shap/_explanation.py
boxhed_shap/_serializable.py
boxhed_shap/datasets.py
boxhed_shap/links.py
boxhed_shap.egg-info/PKG-INFO
boxhed_shap.egg-info/SOURCES.txt
boxhed_shap.egg-info/dependency_links.txt
boxhed_shap.egg-info/not-zip-safe
boxhed_shap.egg-info/requires.txt
boxhed_shap.egg-info/top_level.txt
boxhed_shap/actions/__init__.py
boxhed_shap/actions/_action.py
boxhed_shap/actions/_optimizer.py
boxhed_shap/benchmark/__init__.py
boxhed_shap/benchmark/_compute.py
boxhed_shap/benchmark/_explanation_error.py
boxhed_shap/benchmark/_result.py
boxhed_shap/benchmark/_sequential.py
boxhed_shap/benchmark/experiments.py
boxhed_shap/benchmark/framework.py
boxhed_shap/benchmark/measures.py
boxhed_shap/benchmark/methods.py
boxhed_shap/benchmark/metrics.py
boxhed_shap/benchmark/models.py
boxhed_shap/benchmark/plots.py
boxhed_shap/cext/_cext.cc
boxhed_shap/cext/tree_boxhed_shap.h
boxhed_shap/explainers/__init__.py
boxhed_shap/explainers/_additive.py
boxhed_shap/explainers/_exact.py
boxhed_shap/explainers/_explainer.py
boxhed_shap/explainers/_gpu_tree.py
boxhed_shap/explainers/_gradient.py
boxhed_shap/explainers/_kernel.py
boxhed_shap/explainers/_linear.py
boxhed_shap/explainers/_partition.py
boxhed_shap/explainers/_permutation.py
boxhed_shap/explainers/_sampling.py
boxhed_shap/explainers/_tree.py
boxhed_shap/explainers/mimic.py
boxhed_shap/explainers/pytree.py
boxhed_shap/explainers/tf_utils.py
boxhed_shap/explainers/_deep/__init__.py
boxhed_shap/explainers/_deep/deep_pytorch.py
boxhed_shap/explainers/_deep/deep_tf.py
boxhed_shap/explainers/other/__init__.py
boxhed_shap/explainers/other/_coefficent.py
boxhed_shap/explainers/other/_lime.py
boxhed_shap/explainers/other/_maple.py
boxhed_shap/explainers/other/_random.py
boxhed_shap/explainers/other/_treegain.py
boxhed_shap/maskers/__init__.py
boxhed_shap/maskers/_composite.py
boxhed_shap/maskers/_fixed.py
boxhed_shap/maskers/_fixed_composite.py
boxhed_shap/maskers/_image.py
boxhed_shap/maskers/_masker.py
boxhed_shap/maskers/_output_composite.py
boxhed_shap/maskers/_tabular.py
boxhed_shap/maskers/_text.py
boxhed_shap/models/__init__.py
